shor/__init__.py
shor/algorithms/__init__.py
shor/algorithms/shor.py
shor/errors.py
shor/framework/__init__.py
shor/framework/docstring.py
shor/gates.py
shor/layers.py
shor/operations.py
shor/providers/__init__.py
shor/providers/base.py
shor/providers/qiskit/Aer.py
shor/providers/qiskit/__init__.py
shor/providers/qiskit/base.py
shor/providers/qiskit/ibmq.py
shor/quantum.py
shor/transpilers/__init__.py
shor/transpilers/qiskit.py
shor/utils/__init__.py
shor/utils/collections.py
shor/utils/qbits.py
shor/utils/visual.py
shor-0.0.6.dist-info/LICENSE
shor-0.0.6.dist-info/WHEEL
shor-0.0.6.dist-info/METADATA
shor-0.0.6.dist-info/RECORD
