Metadata-Version: 2.1
Name: shor
Version: 0.0.6
Summary: Quantum Computing for Humans
License: MIT
Author: Collin Overbay - shor.dev
Author-email: shordotdev@gmail.com
Requires-Python: >=3.6.1,<4.0.0
Classifier: License :: OSI Approved :: MIT License
Classifier: Programming Language :: Python :: 3
Classifier: Programming Language :: Python :: 3.7
Classifier: Programming Language :: Python :: 3.8
Classifier: Programming Language :: Python :: 3.9
Requires-Dist: matplotlib (>=3.3.3,<4.0.0)
Requires-Dist: numpy (>=1.19.4,<2.0.0)
Requires-Dist: qiskit (>=0.23.1,<0.24.0)
